pysorters/__init__.py
pysorters/__main__.py
pysorters/automations/__init__.py
pysorters/automations/filepy.py
pysorters/functions/__init__.py
pysorters/functions/methods.py
tests/__init__.py
tests/test_methods.py
pysorters-0.5.6.dist-info/LICENSE
pysorters-0.5.6.dist-info/METADATA
pysorters-0.5.6.dist-info/WHEEL
pysorters-0.5.6.dist-info/top_level.txt
pysorters-0.5.6.dist-info/RECORD
