Metadata-Version: 2.1
Name: pysorters
Version: 0.5.6
Summary: A package with all sorting algorithms.
Home-page: https://github.com/yo1am1/pysorters
Author: yo1
Author-email: bigdiebam@gmail.com
License: MIT
Project-URL: Source, https://github.com/yo1am1/pysorters
Keywords: sorting algorithms,bubble sort,merge sort,quick sort,insertion sort,selection sort,heap sort,radix sort,counting sort,bucket sort,sort,sorting,algorithms,python,pysorters_project
Classifier: Development Status :: 3 - Alpha
Classifier: Programming Language :: Python :: 3.12
Classifier: Programming Language :: Python :: 3.11
Classifier: Programming Language :: Python :: 3.10
Classifier: Intended Audience :: Developers
Classifier: Topic :: Software Development :: Libraries
Classifier: License :: OSI Approved :: MIT License
Classifier: Operating System :: OS Independent
Requires-Python: >=3.10, <=3.12
License-File: LICENSE
Requires-Dist: pytest
